{
  "name": "Health Check",
  "nodes": [
    {
      "parameters": {
        "httpMethod": "GET",
        "path": "health",
        "responseMode": "responseNode",
        "options": {}
      },
      "id": "b1b2c3d4-2222-4000-8000-000000000001",
      "name": "Webhook",
      "type": "n8n-nodes-base.webhook",
      "typeVersion": 2,
      "position": [250, 300],
      "webhookId": "health-check-webhook"
    },
    {
      "parameters": {
        "url": "http://qdrant:6333/collections",
        "options": {
          "timeout": 5000
        }
      },
      "id": "b1b2c3d4-2222-4000-8000-000000000002",
      "name": "Check Qdrant",
      "type": "n8n-nodes-base.httpRequest",
      "typeVersion": 4.2,
      "position": [480, 300]
    },
    {
      "parameters": {
        "assignments": {
          "assignments": [
            {
              "id": "assign-1",
              "name": "status",
              "value": "ok",
              "type": "string"
            },
            {
              "id": "assign-2",
              "name": "timestamp",
              "value": "={{ new Date().toISOString() }}",
              "type": "string"
            },
            {
              "id": "assign-3",
              "name": "services.n8n",
              "value": "healthy",
              "type": "string"
            },
            {
              "id": "assign-4",
              "name": "services.qdrant",
              "value": "healthy",
              "type": "string"
            },
            {
              "id": "assign-5",
              "name": "services.qdrant_collections",
              "value": "={{ $json.result?.collections?.length ?? 0 }}",
              "type": "number"
            }
          ]
        },
        "options": {}
      },
      "id": "b1b2c3d4-2222-4000-8000-000000000003",
      "name": "Build Response",
      "type": "n8n-nodes-base.set",
      "typeVersion": 3.4,
      "position": [710, 300]
    },
    {
      "parameters": {
        "respondWith": "allIncomingItems",
        "options": {}
      },
      "id": "b1b2c3d4-2222-4000-8000-000000000004",
      "name": "Respond to Webhook",
      "type": "n8n-nodes-base.respondToWebhook",
      "typeVersion": 1.1,
      "position": [940, 300]
    }
  ],
  "connections": {
    "Webhook": {
      "main": [
        [
          {
            "node": "Check Qdrant",
            "type": "main",
            "index": 0
          }
        ]
      ]
    },
    "Check Qdrant": {
      "main": [
        [
          {
            "node": "Build Response",
            "type": "main",
            "index": 0
          }
        ]
      ]
    },
    "Build Response": {
      "main": [
        [
          {
            "node": "Respond to Webhook",
            "type": "main",
            "index": 0
          }
        ]
      ]
    }
  },
  "settings": {
    "executionOrder": "v1"
  },
  "pinData": {},
  "staticData": null
}
